pychrono/__init__.py
pychrono/classes.py
pychrono/decorators.py
pychrono/functions.py
pychrono-1.0.6.dist-info/LICENSE
pychrono-1.0.6.dist-info/METADATA
pychrono-1.0.6.dist-info/WHEEL
pychrono-1.0.6.dist-info/top_level.txt
pychrono-1.0.6.dist-info/RECORD
