Metadata-Version: 2.1
Name: pychrono
Version: 1.0.6
Summary: A package for managing delays, scheduling tasks, timing functions, caching results, and enhancing time-based operations with robust decorators for asynchronous execution, throttling, retries, and more.
Author-email: Sébastien <sebastien.works@outlook.com>
Project-URL: Homepage, https://github.com/striatp/Pychrono
Classifier: Programming Language :: Python :: 3.6
Classifier: Programming Language :: Python :: 3.7
Classifier: Programming Language :: Python :: 3.8
Classifier: Programming Language :: Python :: 3.9
Classifier: Programming Language :: Python :: 3.10
Classifier: Programming Language :: Python :: 3.11
Classifier: Programming Language :: Python :: 3.12
Classifier: License :: OSI Approved :: MIT License
Classifier: Operating System :: OS Independent
Requires-Python: >=3.6
License-File: LICENSE
